{
    "46671ab6f7fdf0b43f02b81bbf313fb593de6efb742f921cdde3fdf1398e73e6": {
        "weights": [
            [
                0.0555404730473258,
                0.13964824911270612,
                0.056661139812584076,
                0.08784600269276038,
                0.10114898435082012,
                0.12051323885366887,
                0.12909369189798559,
                0.09372807210890333
            ],
            [
                0.1391671807422622,
                0.11727874740084218,
                0.05036695305919984,
                0.14548618560626808,
                0.06553599742859242,
                0.12192876724734246,
                0.09598750005395537,
                0.11082636245854666
            ],
            [
                0.12848809045274734,
                0.06733788925428233,
                0.0553886671598122,
                0.14984484627333602,
                0.09746502342813215,
                0.06149548804692772,
                0.06262098257471396,
                0.1162941492026352
            ],
            [
                0.11167222086563408,
                0.1465815744346431,
                0.14815576921123835,
                0.11002507111982776,
                0.0617302834667525,
                0.05574164283616387,
                0.13480609967922347,
                0.08136011378503334
            ]
        ],
        "val_acc": 0.9338607594936709,
        "time": 35117.72973752022,
        "zero_cost_scores": {
            "plain": {
                "score": 3.503142833709717,
                "time": 2.4601807594299316
            },
            "params": {
                "score": 3313716,
                "time": 0.6893320083618164
            },
            "flops": {
                "score": 565143278400,
                "time": 0.8685753345489502
            },
            "synflow": {
                "score": 203307517943648.5,
                "time": 0.8723845481872559
            },
            "grad_sign": {
                "score": 3.0301480293273926,
                "time": 3.427417516708374
            },
            "snip": {
                "score": 53.23802947998047,
                "time": 1.019169807434082
            },
            "grad_norm": {
                "score": 7.842651844024658,
                "time": 1.102996826171875
            },
            "epe_nas": {
                "score": 38.47545263564067,
                "time": 1.0520153045654297
            },
            "grasp": {
                "score": -15.116975784301758,
                "time": 3.0542423725128174
            },
            "fisher": {
                "score": 1139.6771240234375,
                "time": 1.223146677017212
            },
            "l2_norm": {
                "score": 722.4178466796875,
                "time": 0.0027234554290771484
            },
            "jacov": {
                "score": -38.258163857944176,
                "time": 1.1662144660949707
            },
            "zen": {
                "score": 33.83806610107422,
                "time": 0.8504984378814697
            },
            "nwot": {
                "score": 166.3140158423559,
                "time": 0.7955131530761719
            }
        },
        "zero_cost_scores_0": {
            "plain": {
                "score": 0.16956189274787903,
                "time": 1.1576721668243408
            },
            "params": {
                "score": 3313716,
                "time": 0.6792490482330322
            },
            "flops": {
                "score": 565143278400,
                "time": 0.8410975933074951
            },
            "synflow": {
                "score": 602401285945463.6,
                "time": 0.9112458229064941
            },
            "grad_sign": {
                "score": 5.29360818862915,
                "time": 2.0432939529418945
            },
            "snip": {
                "score": 39.338417053222656,
                "time": 1.07234525680542
            },
            "grad_norm": {
                "score": 6.178276062011719,
                "time": 1.2078635692596436
            },
            "epe_nas": {
                "score": 6.373791826165914,
                "time": 1.01676607131958
            },
            "grasp": {
                "score": -10.874523162841797,
                "time": 3.1252825260162354
            },
            "fisher": {
                "score": 563.7015991210938,
                "time": 1.1877882480621338
            },
            "l2_norm": {
                "score": 531.7831420898438,
                "time": 0.0027129650115966797
            },
            "jacov": {
                "score": -360.07052749848543,
                "time": 1.1419808864593506
            },
            "zen": {
                "score": 33.28315734863281,
                "time": 0.8012526035308838
            },
            "nwot": {
                "score": 91.84676255594576,
                "time": 0.7361445426940918
            }
        },
        "zero_cost_scores_1": {
            "plain": {
                "score": -0.34460243582725525,
                "time": 1.108060598373413
            },
            "params": {
                "score": 3313716,
                "time": 0.8049972057342529
            },
            "flops": {
                "score": 565143278400,
                "time": 0.7507188320159912
            },
            "synflow": {
                "score": 1744799508280970.5,
                "time": 0.8596172332763672
            },
            "grad_sign": {
                "score": 3.51350998878479,
                "time": 1.9955940246582031
            },
            "snip": {
                "score": 38.89875793457031,
                "time": 1.0724732875823975
            },
            "grad_norm": {
                "score": 8.066337585449219,
                "time": 0.9972751140594482
            },
            "epe_nas": {
                "score": 3.4891331504792413,
                "time": 1.021454095840454
            },
            "grasp": {
                "score": -19.889570236206055,
                "time": 3.070775032043457
            },
            "fisher": {
                "score": 837.203369140625,
                "time": 1.1986830234527588
            },
            "l2_norm": {
                "score": 429.7290954589844,
                "time": 0.0026988983154296875
            },
            "jacov": {
                "score": -210.82504570457814,
                "time": 1.1202688217163086
            },
            "zen": {
                "score": 33.28874588012695,
                "time": 0.9130103588104248
            },
            "nwot": {
                "score": 112.88268963854908,
                "time": 0.8936467170715332
            }
        },
        "zero_cost_scores_2": {
            "plain": {
                "score": -0.2697126269340515,
                "time": 1.0642085075378418
            },
            "params": {
                "score": 3313716,
                "time": 0.750093936920166
            },
            "flops": {
                "score": 565143278400,
                "time": 0.8866763114929199
            },
            "synflow": {
                "score": 4627236392296488.0,
                "time": 0.8321120738983154
            },
            "grad_sign": {
                "score": 3.5190091133117676,
                "time": 2.1435954570770264
            },
            "snip": {
                "score": 44.27106857299805,
                "time": 1.1194307804107666
            },
            "grad_norm": {
                "score": 5.963281631469727,
                "time": 1.1251342296600342
            },
            "epe_nas": {
                "score": 2.030327495386039,
                "time": 1.056671142578125
            },
            "grasp": {
                "score": -8.118103981018066,
                "time": 3.115718126296997
            },
            "fisher": {
                "score": 563.3259887695312,
                "time": 1.2495384216308594
            },
            "l2_norm": {
                "score": 380.0679016113281,
                "time": 0.0027098655700683594
            },
            "jacov": {
                "score": -103.47003920354281,
                "time": 1.0802154541015625
            },
            "zen": {
                "score": 33.719688415527344,
                "time": 0.8938848972320557
            },
            "nwot": {
                "score": 165.93498667044264,
                "time": 0.7831771373748779
            }
        },
        "zero_cost_scores_3": {
            "plain": {
                "score": 0.06375984102487564,
                "time": 1.0597269535064697
            },
            "params": {
                "score": 3313716,
                "time": 0.7540779113769531
            },
            "flops": {
                "score": 565143278400,
                "time": 0.8123171329498291
            },
            "synflow": {
                "score": 8637345331148140.0,
                "time": 0.8567187786102295
            },
            "grad_sign": {
                "score": 4.271686553955078,
                "time": 2.1158430576324463
            },
            "snip": {
                "score": 41.38189697265625,
                "time": 1.1597075462341309
            },
            "grad_norm": {
                "score": 4.833371162414551,
                "time": 1.1546270847320557
            },
            "epe_nas": {
                "score": 15.653159776491073,
                "time": 1.051950216293335
            },
            "grasp": {
                "score": -15.422005653381348,
                "time": 3.1349658966064453
            },
            "fisher": {
                "score": 437.198974609375,
                "time": 1.3470268249511719
            },
            "l2_norm": {
                "score": 355.2647705078125,
                "time": 0.0027065277099609375
            },
            "jacov": {
                "score": -85.35508626621134,
                "time": 1.1664626598358154
            },
            "zen": {
                "score": 33.70183563232422,
                "time": 0.9913537502288818
            },
            "nwot": {
                "score": 55.61521935672281,
                "time": 0.8742995262145996
            }
        },
        "zero_cost_scores_4": {
            "plain": {
                "score": -0.003631308674812317,
                "time": 1.0344884395599365
            },
            "params": {
                "score": 3313716,
                "time": 0.6555335521697998
            },
            "flops": {
                "score": 565143278400,
                "time": 0.8579003810882568
            },
            "synflow": {
                "score": 1.204934153672253e+16,
                "time": 0.833080530166626
            },
            "grad_sign": {
                "score": 3.620940685272217,
                "time": 2.1051676273345947
            },
            "snip": {
                "score": 43.97309494018555,
                "time": 1.139909267425537
            },
            "grad_norm": {
                "score": 9.228300094604492,
                "time": 1.0379066467285156
            },
            "epe_nas": {
                "score": 5.07829150573818,
                "time": 1.0369367599487305
            },
            "grasp": {
                "score": -41.712345123291016,
                "time": 3.105278253555298
            },
            "fisher": {
                "score": 582.8471069335938,
                "time": 1.1932101249694824
            },
            "l2_norm": {
                "score": 341.3887634277344,
                "time": 0.0027208328247070312
            },
            "jacov": {
                "score": -95.575491300518,
                "time": 1.1687593460083008
            },
            "zen": {
                "score": 33.417545318603516,
                "time": 0.866551399230957
            },
            "nwot": {
                "score": 79.94500291952993,
                "time": 0.7686231136322021
            }
        },
        "zero_cost_scores_5": {
            "plain": {
                "score": -0.010622024536132812,
                "time": 1.1135611534118652
            },
            "params": {
                "score": 3313716,
                "time": 0.7279202938079834
            },
            "flops": {
                "score": 565143278400,
                "time": 0.732241153717041
            },
            "synflow": {
                "score": 1.5764289034400392e+16,
                "time": 0.9607555866241455
            },
            "grad_sign": {
                "score": 4.208356857299805,
                "time": 2.103215456008911
            },
            "snip": {
                "score": 39.89277267456055,
                "time": 1.0820977687835693
            },
            "grad_norm": {
                "score": 6.0650224685668945,
                "time": 1.0368857383728027
            },
            "epe_nas": {
                "score": 14.142917625951739,
                "time": 1.0619480609893799
            },
            "grasp": {
                "score": -13.729592323303223,
                "time": 3.097026824951172
            },
            "fisher": {
                "score": 465.1611328125,
                "time": 1.2121448516845703
            },
            "l2_norm": {
                "score": 334.3161315917969,
                "time": 0.0027256011962890625
            },
            "jacov": {
                "score": -114.86648543336312,
                "time": 1.2106144428253174
            },
            "zen": {
                "score": 33.631103515625,
                "time": 0.8818321228027344
            },
            "nwot": {
                "score": 106.39894821436219,
                "time": 0.7363090515136719
            }
        },
        "zero_cost_scores_6": {
            "plain": {
                "score": 0.12927132844924927,
                "time": 0.9825620651245117
            },
            "params": {
                "score": 3313716,
                "time": 0.822242259979248
            },
            "flops": {
                "score": 565143278400,
                "time": 0.6967473030090332
            },
            "synflow": {
                "score": 1.8995251961723508e+16,
                "time": 0.9096543788909912
            },
            "grad_sign": {
                "score": 5.250545978546143,
                "time": 2.0681867599487305
            },
            "snip": {
                "score": 43.961036682128906,
                "time": 1.0508077144622803
            },
            "grad_norm": {
                "score": 6.279730796813965,
                "time": 1.0506315231323242
            },
            "epe_nas": {
                "score": 3.9089422003146197,
                "time": 1.0317151546478271
            },
            "grasp": {
                "score": -15.498353958129883,
                "time": 3.0324745178222656
            },
            "fisher": {
                "score": 563.5082397460938,
                "time": 1.2306602001190186
            },
            "l2_norm": {
                "score": 330.19403076171875,
                "time": 0.0027132034301757812
            },
            "jacov": {
                "score": -71.52383394598527,
                "time": 1.0177369117736816
            },
            "zen": {
                "score": 33.53017807006836,
                "time": 0.933300256729126
            },
            "nwot": {
                "score": 181.73374972027702,
                "time": 0.8873958587646484
            }
        },
        "zero_cost_scores_7": {
            "plain": {
                "score": -0.13841462135314941,
                "time": 1.1492443084716797
            },
            "params": {
                "score": 3313716,
                "time": 0.661440372467041
            },
            "flops": {
                "score": 565143278400,
                "time": 0.755760669708252
            },
            "synflow": {
                "score": 2.336123034668347e+16,
                "time": 0.981680154800415
            },
            "grad_sign": {
                "score": 4.56504487991333,
                "time": 2.038398027420044
            },
            "snip": {
                "score": 30.338092803955078,
                "time": 1.094461441040039
            },
            "grad_norm": {
                "score": 6.181312561035156,
                "time": 1.0542590618133545
            },
            "epe_nas": {
                "score": 11.42077854517174,
                "time": 1.0326159000396729
            },
            "grasp": {
                "score": -10.912120819091797,
                "time": 3.023918390274048
            },
            "fisher": {
                "score": 362.94403076171875,
                "time": 1.219775676727295
            },
            "l2_norm": {
                "score": 328.5994873046875,
                "time": 0.002721071243286133
            },
            "jacov": {
                "score": -67.2041370318203,
                "time": 1.3008484840393066
            },
            "zen": {
                "score": 33.68012237548828,
                "time": 0.9883689880371094
            },
            "nwot": {
                "score": 187.27012548588735,
                "time": 0.776874303817749
            }
        },
        "zero_cost_scores_8": {
            "plain": {
                "score": -0.38967934250831604,
                "time": 1.0524652004241943
            },
            "params": {
                "score": 3313716,
                "time": 0.7696793079376221
            },
            "flops": {
                "score": 565143278400,
                "time": 0.8119988441467285
            },
            "synflow": {
                "score": 2.425782057869872e+16,
                "time": 0.8885667324066162
            },
            "grad_sign": {
                "score": 4.969028472900391,
                "time": 2.1763691902160645
            },
            "snip": {
                "score": 38.52489471435547,
                "time": 0.9752123355865479
            },
            "grad_norm": {
                "score": 5.065948009490967,
                "time": 1.0837972164154053
            },
            "epe_nas": {
                "score": 26.08685458369008,
                "time": 0.9912891387939453
            },
            "grasp": {
                "score": -11.782693862915039,
                "time": 3.0607941150665283
            },
            "fisher": {
                "score": 405.1507873535156,
                "time": 1.1424896717071533
            },
            "l2_norm": {
                "score": 326.9449768066406,
                "time": 0.0027112960815429688
            },
            "jacov": {
                "score": -76.4260165789424,
                "time": 1.0873134136199951
            },
            "zen": {
                "score": 33.85011291503906,
                "time": 0.9847373962402344
            },
            "nwot": {
                "score": 188.77535528230248,
                "time": 0.7768764495849609
            }
        },
        "zero_cost_scores_9": {
            "plain": {
                "score": -0.6266155242919922,
                "time": 1.2021467685699463
            },
            "params": {
                "score": 3313716,
                "time": 0.8505494594573975
            },
            "flops": {
                "score": 565143278400,
                "time": 0.7503252029418945
            },
            "synflow": {
                "score": 2.677592683598272e+16,
                "time": 0.8429617881774902
            },
            "grad_sign": {
                "score": 4.72624397277832,
                "time": 2.0899205207824707
            },
            "snip": {
                "score": 41.49602508544922,
                "time": 0.9903626441955566
            },
            "grad_norm": {
                "score": 5.339934349060059,
                "time": 1.073023796081543
            },
            "epe_nas": {
                "score": 6.244840324237333,
                "time": 1.0734801292419434
            },
            "grasp": {
                "score": -7.4039411544799805,
                "time": 3.108718156814575
            },
            "fisher": {
                "score": 318.4263916015625,
                "time": 1.3085126876831055
            },
            "l2_norm": {
                "score": 325.73638916015625,
                "time": 0.002718210220336914
            },
            "jacov": {
                "score": -116.75389319417064,
                "time": 1.1087055206298828
            },
            "zen": {
                "score": 33.670310974121094,
                "time": 0.8834629058837891
            },
            "nwot": {
                "score": 67.84398940500654,
                "time": 0.813277006149292
            }
        },
        "zero_cost_scores_11": {
            "plain": {
                "score": -0.4319988191127777,
                "time": 1.092395305633545
            },
            "params": {
                "score": 3313716,
                "time": 0.813023567199707
            },
            "flops": {
                "score": 565143278400,
                "time": 0.790555477142334
            },
            "synflow": {
                "score": 2.7920729487050384e+16,
                "time": 0.8657469749450684
            },
            "grad_sign": {
                "score": 4.606545448303223,
                "time": 2.087172746658325
            },
            "snip": {
                "score": 38.86827850341797,
                "time": 1.0517046451568604
            },
            "grad_norm": {
                "score": 5.375192165374756,
                "time": 1.1082112789154053
            },
            "epe_nas": {
                "score": 6.82947455615682,
                "time": 1.0676822662353516
            },
            "grasp": {
                "score": -6.28823184967041,
                "time": 3.0308737754821777
            },
            "fisher": {
                "score": 346.0484924316406,
                "time": 1.1687684059143066
            },
            "l2_norm": {
                "score": 324.01416015625,
                "time": 0.0027146339416503906
            },
            "jacov": {
                "score": -200091.31543079123,
                "time": 1.0173957347869873
            },
            "zen": {
                "score": 33.610496520996094,
                "time": 0.9362854957580566
            },
            "nwot": {
                "score": 167.89915410593247,
                "time": 0.7863755226135254
            }
        },
        "zero_cost_scores_13": {
            "plain": {
                "score": -0.14789646863937378,
                "time": 1.059108018875122
            },
            "params": {
                "score": 3313716,
                "time": 0.7419426441192627
            },
            "flops": {
                "score": 565143278400,
                "time": 0.8297898769378662
            },
            "synflow": {
                "score": 3.0807087174108052e+16,
                "time": 0.9014503955841064
            },
            "grad_sign": {
                "score": 4.411690711975098,
                "time": 2.0998775959014893
            },
            "snip": {
                "score": 33.925819396972656,
                "time": 1.0778648853302002
            },
            "grad_norm": {
                "score": 5.0721116065979,
                "time": 1.0530242919921875
            },
            "epe_nas": {
                "score": 5.209073047765907,
                "time": 0.9770472049713135
            },
            "grasp": {
                "score": -8.749066352844238,
                "time": 3.005985736846924
            },
            "fisher": {
                "score": 330.6839599609375,
                "time": 1.1565022468566895
            },
            "l2_norm": {
                "score": 324.91717529296875,
                "time": 0.002787351608276367
            },
            "jacov": {
                "score": -86.66136569513813,
                "time": 1.254629135131836
            },
            "zen": {
                "score": 33.70820236206055,
                "time": 0.8459784984588623
            },
            "nwot": {
                "score": 108.16180077343171,
                "time": 0.8347172737121582
            }
        },
        "zero_cost_scores_15": {
            "plain": {
                "score": 0.21286940574645996,
                "time": 1.0377771854400635
            },
            "params": {
                "score": 3313716,
                "time": 0.759124755859375
            },
            "flops": {
                "score": 565143278400,
                "time": 0.755305290222168
            },
            "synflow": {
                "score": 3.4886818582534468e+16,
                "time": 0.9263715744018555
            },
            "grad_sign": {
                "score": 4.439328670501709,
                "time": 2.0769524574279785
            },
            "snip": {
                "score": 40.66622543334961,
                "time": 1.0906496047973633
            },
            "grad_norm": {
                "score": 7.284841060638428,
                "time": 1.0401537418365479
            },
            "epe_nas": {
                "score": 3.6315941927352036,
                "time": 1.044538974761963
            },
            "grasp": {
                "score": -27.801837921142578,
                "time": 3.020993232727051
            },
            "fisher": {
                "score": 571.387939453125,
                "time": 1.2686712741851807
            },
            "l2_norm": {
                "score": 326.8851013183594,
                "time": 0.0027136802673339844
            },
            "jacov": {
                "score": -75.58939125329205,
                "time": 1.1080915927886963
            },
            "zen": {
                "score": 33.629920959472656,
                "time": 0.9155757427215576
            },
            "nwot": {
                "score": 109.51905859304844,
                "time": 0.7903265953063965
            }
        },
        "zero_cost_scores_17": {
            "plain": {
                "score": 0.21213607490062714,
                "time": 1.043076992034912
            },
            "params": {
                "score": 3313716,
                "time": 0.6805722713470459
            },
            "flops": {
                "score": 565143278400,
                "time": 0.8307206630706787
            },
            "synflow": {
                "score": 1.3660570200750458e+16,
                "time": 0.9275269508361816
            },
            "grad_sign": {
                "score": 3.2222304344177246,
                "time": 2.11872935295105
            },
            "snip": {
                "score": 31.604307174682617,
                "time": 1.0959446430206299
            },
            "grad_norm": {
                "score": 3.921387195587158,
                "time": 1.1672792434692383
            },
            "epe_nas": {
                "score": 9.43019256210738,
                "time": 1.0495333671569824
            },
            "grasp": {
                "score": -2.4287302494049072,
                "time": 3.289935350418091
            },
            "fisher": {
                "score": 274.31634521484375,
                "time": 1.357239007949829
            },
            "l2_norm": {
                "score": 312.88079833984375,
                "time": 0.0027565956115722656
            },
            "jacov": {
                "score": -167.01456068217755,
                "time": 1.1178226470947266
            },
            "zen": {
                "score": 33.15727233886719,
                "time": 0.9296989440917969
            },
            "nwot": {
                "score": 75.08478149468056,
                "time": 0.877525806427002
            }
        },
        "zero_cost_scores_19": {
            "plain": {
                "score": -0.14416034519672394,
                "time": 0.9783406257629395
            },
            "params": {
                "score": 3313716,
                "time": 0.7664601802825928
            },
            "flops": {
                "score": 565143278400,
                "time": 0.743330717086792
            },
            "synflow": {
                "score": 1.8719656503684324e+16,
                "time": 0.8298807144165039
            },
            "grad_sign": {
                "score": 4.201903343200684,
                "time": 2.0979223251342773
            },
            "snip": {
                "score": 30.58716583251953,
                "time": 1.053659200668335
            },
            "grad_norm": {
                "score": 6.359097957611084,
                "time": 1.1821215152740479
            },
            "epe_nas": {
                "score": 11.947973908049336,
                "time": 1.1707520484924316
            },
            "grasp": {
                "score": -22.1574764251709,
                "time": 3.0939600467681885
            },
            "fisher": {
                "score": 267.5693359375,
                "time": 1.3469009399414062
            },
            "l2_norm": {
                "score": 317.33795166015625,
                "time": 0.0027313232421875
            },
            "jacov": {
                "score": -100068.38561339391,
                "time": 1.1088645458221436
            },
            "zen": {
                "score": 33.56866455078125,
                "time": 0.9055545330047607
            },
            "nwot": {
                "score": 125.67017051363948,
                "time": 0.7983672618865967
            }
        },
        "zero_cost_scores_21": {
            "plain": {
                "score": -0.1873319149017334,
                "time": 1.1844422817230225
            },
            "params": {
                "score": 3313716,
                "time": 0.7804234027862549
            },
            "flops": {
                "score": 565143278400,
                "time": 0.9167881011962891
            },
            "synflow": {
                "score": 2.5347243769022604e+16,
                "time": 0.93227219581604
            },
            "grad_sign": {
                "score": 4.716794013977051,
                "time": 2.163951873779297
            },
            "snip": {
                "score": 30.22772216796875,
                "time": 1.0024151802062988
            },
            "grad_norm": {
                "score": 3.7796287536621094,
                "time": 0.9673731327056885
            },
            "epe_nas": {
                "score": 6.068978345422226,
                "time": 0.9299519062042236
            },
            "grasp": {
                "score": -10.47459602355957,
                "time": 3.0929901599884033
            },
            "fisher": {
                "score": 456.6834411621094,
                "time": 1.1767539978027344
            },
            "l2_norm": {
                "score": 322.2571105957031,
                "time": 0.0027120113372802734
            },
            "jacov": {
                "score": -100094.4930002238,
                "time": 1.0483131408691406
            },
            "zen": {
                "score": 33.43584060668945,
                "time": 0.9018473625183105
            },
            "nwot": {
                "score": 104.11994924271599,
                "time": 0.8994247913360596
            }
        },
        "zero_cost_scores_23": {
            "plain": {
                "score": -0.31497544050216675,
                "time": 1.232492208480835
            },
            "params": {
                "score": 3313716,
                "time": 0.8470003604888916
            },
            "flops": {
                "score": 565143278400,
                "time": 0.7366163730621338
            },
            "synflow": {
                "score": 3.165303820712856e+16,
                "time": 0.9126095771789551
            },
            "grad_sign": {
                "score": 6.100683212280273,
                "time": 2.0410478115081787
            },
            "snip": {
                "score": 34.932373046875,
                "time": 1.0674080848693848
            },
            "grad_norm": {
                "score": 5.543783187866211,
                "time": 1.1447882652282715
            },
            "epe_nas": {
                "score": 8.528997790722242,
                "time": 0.949674129486084
            },
            "grasp": {
                "score": -8.506828308105469,
                "time": 3.071787118911743
            },
            "fisher": {
                "score": 316.2672424316406,
                "time": 1.1382746696472168
            },
            "l2_norm": {
                "score": 325.2269287109375,
                "time": 0.002723217010498047
            },
            "jacov": {
                "score": -131.28021174480045,
                "time": 1.0607459545135498
            },
            "zen": {
                "score": 33.587554931640625,
                "time": 0.9918980598449707
            },
            "nwot": {
                "score": 100.95178152539816,
                "time": 0.843839168548584
            }
        },
        "zero_cost_scores_25": {
            "plain": {
                "score": 0.17353054881095886,
                "time": 1.1071641445159912
            },
            "params": {
                "score": 3313716,
                "time": 0.7245974540710449
            },
            "flops": {
                "score": 565143278400,
                "time": 0.8140280246734619
            },
            "synflow": {
                "score": 3.5639056505328388e+16,
                "time": 0.8054468631744385
            },
            "grad_sign": {
                "score": 3.2931175231933594,
                "time": 2.1708412170410156
            },
            "snip": {
                "score": 24.80662727355957,
                "time": 0.9995274543762207
            },
            "grad_norm": {
                "score": 4.365863800048828,
                "time": 1.0731205940246582
            },
            "epe_nas": {
                "score": 8.04552693975573,
                "time": 1.0974228382110596
            },
            "grasp": {
                "score": -4.7215070724487305,
                "time": 3.074260950088501
            },
            "fisher": {
                "score": 249.80990600585938,
                "time": 1.1673688888549805
            },
            "l2_norm": {
                "score": 328.00421142578125,
                "time": 0.002688169479370117
            },
            "jacov": {
                "score": -106.39741173903063,
                "time": 1.1796975135803223
            },
            "zen": {
                "score": 33.70499038696289,
                "time": 0.9417154788970947
            },
            "nwot": {
                "score": 101.25091144779047,
                "time": 0.7823047637939453
            }
        },
        "zero_cost_scores_27": {
            "plain": {
                "score": 0.20323999226093292,
                "time": 1.0343928337097168
            },
            "params": {
                "score": 3313716,
                "time": 0.7978775501251221
            },
            "flops": {
                "score": 565143278400,
                "time": 0.8061795234680176
            },
            "synflow": {
                "score": 4.213762152543397e+16,
                "time": 0.8823306560516357
            },
            "grad_sign": {
                "score": 2.990675926208496,
                "time": 2.106872797012329
            },
            "snip": {
                "score": 36.31297302246094,
                "time": 1.2307155132293701
            },
            "grad_norm": {
                "score": 7.646853446960449,
                "time": 1.089646816253662
            },
            "epe_nas": {
                "score": 3.951257565307139,
                "time": 1.0446102619171143
            },
            "grasp": {
                "score": -18.972883224487305,
                "time": 3.096646308898926
            },
            "fisher": {
                "score": 455.1834716796875,
                "time": 1.1358025074005127
            },
            "l2_norm": {
                "score": 330.17962646484375,
                "time": 0.0026929378509521484
            },
            "jacov": {
                "score": -118.65182335230396,
                "time": 1.075080156326294
            },
            "zen": {
                "score": 33.50619888305664,
                "time": 1.0170745849609375
            },
            "nwot": {
                "score": 99.74814625197918,
                "time": 0.7932262420654297
            }
        },
        "zero_cost_scores_29": {
            "plain": {
                "score": -0.2960878610610962,
                "time": 1.013930320739746
            },
            "params": {
                "score": 3313716,
                "time": 0.7756741046905518
            },
            "flops": {
                "score": 565143278400,
                "time": 0.7829113006591797
            },
            "synflow": {
                "score": 5.1741489533223656e+16,
                "time": 0.8453264236450195
            },
            "grad_sign": {
                "score": 4.2364349365234375,
                "time": 2.132352352142334
            },
            "snip": {
                "score": 26.712650299072266,
                "time": 0.9639909267425537
            },
            "grad_norm": {
                "score": 5.801882266998291,
                "time": 1.201730489730835
            },
            "epe_nas": {
                "score": 0.0001999990000079768,
                "time": 0.9987888336181641
            },
            "grasp": {
                "score": -22.52912139892578,
                "time": 3.131471872329712
            },
            "fisher": {
                "score": 167.1007843017578,
                "time": 1.1733853816986084
            },
            "l2_norm": {
                "score": 333.9420471191406,
                "time": 0.0026865005493164062
            },
            "jacov": {
                "score": -149.1158741847686,
                "time": 1.0568039417266846
            },
            "zen": {
                "score": 33.68144989013672,
                "time": 0.9600729942321777
            },
            "nwot": {
                "score": 83.30417140535178,
                "time": 0.7779045104980469
            }
        },
        "zero_cost_scores_31": {
            "plain": {
                "score": -0.4161847233772278,
                "time": 1.055006980895996
            },
            "params": {
                "score": 3313716,
                "time": 0.7110741138458252
            },
            "flops": {
                "score": 565143278400,
                "time": 0.809389591217041
            },
            "synflow": {
                "score": 1.9788431366356956e+16,
                "time": 0.8586349487304688
            },
            "grad_sign": {
                "score": 4.682844161987305,
                "time": 2.1359376907348633
            },
            "snip": {
                "score": 33.07118225097656,
                "time": 1.0985941886901855
            },
            "grad_norm": {
                "score": 4.532208442687988,
                "time": 1.2032420635223389
            },
            "epe_nas": {
                "score": 8.473079128022269,
                "time": 1.033677577972412
            },
            "grasp": {
                "score": -12.46975326538086,
                "time": 3.0757150650024414
            },
            "fisher": {
                "score": 472.8479309082031,
                "time": 1.19466233253479
            },
            "l2_norm": {
                "score": 318.8619384765625,
                "time": 0.0028409957885742188
            },
            "jacov": {
                "score": -94.06875997683777,
                "time": 1.1604101657867432
            },
            "zen": {
                "score": 33.43081283569336,
                "time": 0.9784703254699707
            },
            "nwot": {
                "score": 82.61531959218694,
                "time": 0.8459351062774658
            }
        },
        "zero_cost_scores_33": {
            "plain": {
                "score": -0.3017404079437256,
                "time": 1.0325472354888916
            },
            "params": {
                "score": 3313716,
                "time": 0.6727917194366455
            },
            "flops": {
                "score": 565143278400,
                "time": 0.8642041683197021
            },
            "synflow": {
                "score": 8552569246248279.0,
                "time": 0.8820953369140625
            },
            "grad_sign": {
                "score": 4.36601448059082,
                "time": 2.073216199874878
            },
            "snip": {
                "score": 24.839069366455078,
                "time": 1.1412973403930664
            },
            "grad_norm": {
                "score": 4.45410680770874,
                "time": 1.1696903705596924
            },
            "epe_nas": {
                "score": 0.8294423895422364,
                "time": 1.1362380981445312
            },
            "grasp": {
                "score": -6.112086772918701,
                "time": 3.1390459537506104
            },
            "fisher": {
                "score": 329.62042236328125,
                "time": 1.2423889636993408
            },
            "l2_norm": {
                "score": 306.7403564453125,
                "time": 0.002706766128540039
            },
            "jacov": {
                "score": -117.4462901757722,
                "time": 1.0589656829833984
            },
            "zen": {
                "score": 33.161956787109375,
                "time": 0.9010124206542969
            },
            "nwot": {
                "score": 158.2886906364016,
                "time": 0.8323867321014404
            }
        },
        "zero_cost_scores_35": {
            "plain": {
                "score": -0.1406542807817459,
                "time": 1.0029428005218506
            },
            "params": {
                "score": 3313716,
                "time": 0.6777331829071045
            },
            "flops": {
                "score": 565143278400,
                "time": 0.8300638198852539
            },
            "synflow": {
                "score": 4286037994154562.5,
                "time": 0.8537418842315674
            },
            "grad_sign": {
                "score": 3.686201333999634,
                "time": 2.098834276199341
            },
            "snip": {
                "score": 29.609512329101562,
                "time": 1.022881269454956
            },
            "grad_norm": {
                "score": 4.5927863121032715,
                "time": 1.0420291423797607
            },
            "epe_nas": {
                "score": 14.572011177197052,
                "time": 1.0937273502349854
            },
            "grasp": {
                "score": -8.176214218139648,
                "time": 3.098841428756714
            },
            "fisher": {
                "score": 298.7549133300781,
                "time": 1.2680137157440186
            },
            "l2_norm": {
                "score": 297.52032470703125,
                "time": 0.0026912689208984375
            },
            "jacov": {
                "score": -106.46572459669977,
                "time": 1.1590652465820312
            },
            "zen": {
                "score": 32.97776794433594,
                "time": 0.9485561847686768
            },
            "nwot": {
                "score": 148.55211881189527,
                "time": 0.7139337062835693
            }
        },
        "zero_cost_scores_37": {
            "plain": {
                "score": -0.03732125833630562,
                "time": 1.0111110210418701
            },
            "params": {
                "score": 3313716,
                "time": 0.695457935333252
            },
            "flops": {
                "score": 565143278400,
                "time": 0.8839802742004395
            },
            "synflow": {
                "score": 2595740514556005.0,
                "time": 0.9548077583312988
            },
            "grad_sign": {
                "score": 2.919842004776001,
                "time": 2.1823694705963135
            },
            "snip": {
                "score": 31.86017417907715,
                "time": 1.0721657276153564
            },
            "grad_norm": {
                "score": 4.547468185424805,
                "time": 1.0467314720153809
            },
            "epe_nas": {
                "score": 8.146307632518047,
                "time": 1.1118755340576172
            },
            "grasp": {
                "score": -14.446864128112793,
                "time": 3.2010385990142822
            },
            "fisher": {
                "score": 321.41729736328125,
                "time": 1.1862967014312744
            },
            "l2_norm": {
                "score": 291.1512451171875,
                "time": 0.0027112960815429688
            },
            "jacov": {
                "score": -151.01965628729246,
                "time": 1.102734088897705
            },
            "zen": {
                "score": 32.758663177490234,
                "time": 0.8990468978881836
            },
            "nwot": {
                "score": 151.29083082853379,
                "time": 0.8527636528015137
            }
        },
        "zero_cost_scores_39": {
            "plain": {
                "score": -0.3913980722427368,
                "time": 1.1505544185638428
            },
            "params": {
                "score": 3313716,
                "time": 0.7925055027008057
            },
            "flops": {
                "score": 565143278400,
                "time": 0.9504857063293457
            },
            "synflow": {
                "score": 1808866514553121.8,
                "time": 0.8684992790222168
            },
            "grad_sign": {
                "score": 2.301668405532837,
                "time": 2.0685529708862305
            },
            "snip": {
                "score": 27.081451416015625,
                "time": 1.0178217887878418
            },
            "grad_norm": {
                "score": 5.701511383056641,
                "time": 1.1027841567993164
            },
            "epe_nas": {
                "score": 0.0001999990000079768,
                "time": 1.0255825519561768
            },
            "grasp": {
                "score": -16.4190731048584,
                "time": 2.99139142036438
            },
            "fisher": {
                "score": 375.3325500488281,
                "time": 1.1879761219024658
            },
            "l2_norm": {
                "score": 286.89801025390625,
                "time": 0.002805948257446289
            },
            "jacov": {
                "score": -80.70690226547316,
                "time": 1.0480258464813232
            },
            "zen": {
                "score": 32.482635498046875,
                "time": 0.9056520462036133
            },
            "nwot": {
                "score": 72.61565804482495,
                "time": 0.827399730682373
            }
        },
        "zero_cost_scores_41": {
            "plain": {
                "score": -0.14703375101089478,
                "time": 1.2158126831054688
            },
            "params": {
                "score": 3313716,
                "time": 0.7621304988861084
            },
            "flops": {
                "score": 565143278400,
                "time": 0.7879457473754883
            },
            "synflow": {
                "score": 1494101818034758.5,
                "time": 0.8371219635009766
            },
            "grad_sign": {
                "score": 2.246361494064331,
                "time": 2.119749069213867
            },
            "snip": {
                "score": 28.80767059326172,
                "time": 1.0140297412872314
            },
            "grad_norm": {
                "score": 6.307325839996338,
                "time": 1.020864725112915
            },
            "epe_nas": {
                "score": 8.549492070322621,
                "time": 1.0554563999176025
            },
            "grasp": {
                "score": -16.230499267578125,
                "time": 3.1214382648468018
            },
            "fisher": {
                "score": 310.5818786621094,
                "time": 1.1470997333526611
            },
            "l2_norm": {
                "score": 284.75811767578125,
                "time": 0.002714395523071289
            },
            "jacov": {
                "score": -82.34350466951595,
                "time": 1.1292693614959717
            },
            "zen": {
                "score": 32.57582473754883,
                "time": 0.9382338523864746
            },
            "nwot": {
                "score": 212.8523069965404,
                "time": 0.7961912155151367
            }
        },
        "zero_cost_scores_43": {
            "plain": {
                "score": -0.23858876526355743,
                "time": 1.0413823127746582
            },
            "params": {
                "score": 3313716,
                "time": 0.6994102001190186
            },
            "flops": {
                "score": 565143278400,
                "time": 0.8301975727081299
            },
            "synflow": {
                "score": 1340972580285916.0,
                "time": 0.8081240653991699
            },
            "grad_sign": {
                "score": 2.715426445007324,
                "time": 2.11549711227417
            },
            "snip": {
                "score": 27.79100799560547,
                "time": 1.066758394241333
            },
            "grad_norm": {
                "score": 5.022729873657227,
                "time": 1.1147701740264893
            },
            "epe_nas": {
                "score": 18.45397076544625,
                "time": 1.090871810913086
            },
            "grasp": {
                "score": -11.459493637084961,
                "time": 3.089540481567383
            },
            "fisher": {
                "score": 274.9258117675781,
                "time": 1.2069065570831299
            },
            "l2_norm": {
                "score": 283.6968688964844,
                "time": 0.0027146339416503906
            },
            "jacov": {
                "score": -125.99063604972598,
                "time": 1.0311522483825684
            },
            "zen": {
                "score": 32.51183319091797,
                "time": 0.855642557144165
            },
            "nwot": {
                "score": 161.18864719138685,
                "time": 0.9036028385162354
            }
        },
        "zero_cost_scores_45": {
            "plain": {
                "score": -0.15339848399162292,
                "time": 1.2398192882537842
            },
            "params": {
                "score": 3313716,
                "time": 0.7155964374542236
            },
            "flops": {
                "score": 565143278400,
                "time": 0.7433106899261475
            },
            "synflow": {
                "score": 1239696493221238.0,
                "time": 0.8965182304382324
            },
            "grad_sign": {
                "score": 2.728940725326538,
                "time": 2.160245418548584
            },
            "snip": {
                "score": 28.15444564819336,
                "time": 1.0545799732208252
            },
            "grad_norm": {
                "score": 5.501844882965088,
                "time": 1.1257994174957275
            },
            "epe_nas": {
                "score": 31.088084332891118,
                "time": 1.0493907928466797
            },
            "grasp": {
                "score": -10.536301612854004,
                "time": 3.0629687309265137
            },
            "fisher": {
                "score": 290.621337890625,
                "time": 1.2201194763183594
            },
            "l2_norm": {
                "score": 282.9525451660156,
                "time": 0.002732992172241211
            },
            "jacov": {
                "score": -277.36834785654764,
                "time": 1.1206300258636475
            },
            "zen": {
                "score": 32.434303283691406,
                "time": 1.046635627746582
            },
            "nwot": {
                "score": 161.79650986445864,
                "time": 0.8038012981414795
            }
        }
    }
}