{
    "aaa4d2419e94715ce06cd712142846d44e1a3b78449f5be1665fbf1ceb59d2fd": {
        "weights": [
            [
                0.08494322161222459,
                0.05055922279141886,
                0.08587238441557139,
                0.11508794396098584,
                0.09408103565714598,
                0.11992359778257973,
                0.11315873544106324,
                0.11207022735191291
            ],
            [
                0.0570814318978805,
                0.11668553596030928,
                0.13973092481385846,
                0.07636566593021361,
                0.14879528112763699,
                0.07515134048272426,
                0.11757198306895346,
                0.1450482504514299
            ],
            [
                0.07309477861990502,
                0.11486578239277347,
                0.058291749428900134,
                0.05490969130235938,
                0.08001551832202693,
                0.08651997321087193,
                0.05233816653003305,
                0.114162294623613
            ],
            [
                0.09318233627184255,
                0.06996206623382992,
                0.11586642141984103,
                0.09575207343071132,
                0.13372896463525608,
                0.13521629971243426,
                0.08538126352854244,
                0.09660163169622638
            ],
            [
                0.08068601040646746,
                0.05885519819122092,
                0.10087693671348649,
                0.10963969816820948,
                0.06159754795339916,
                0.062364216981171006,
                0.14704075890654195,
                0.05878894633738499
            ],
            [
                0.06002425979672826,
                0.14317692234683643,
                0.08824734543857612,
                0.12247538580793796,
                0.09160086361403683,
                0.08993337895255274,
                0.11353808338635568,
                0.10065125727435156
            ],
            [
                0.13540007606137427,
                0.09600935575375211,
                0.11120784092665162,
                0.052359262297295456,
                0.1423538082712073,
                0.05917220785326041,
                0.13426818650672612,
                0.061896944654190655
            ],
            [
                0.052705738841462894,
                0.08083530808385944,
                0.08526152529215789,
                0.09703164323168659,
                0.1387004981803419,
                0.05335144024371246,
                0.11452954591101794,
                0.05705968560623741
            ]
        ],
        "val_acc": 0.9429852320675105,
        "time": 45685.014585494995,
        "zero_cost_scores": {
            "plain": {
                "score": 3.691742420196533,
                "time": 3.2573413848876953
            },
            "params": {
                "score": 4513632,
                "time": 1.160905122756958
            },
            "flops": {
                "score": 1015520342400,
                "time": 1.1357529163360596
            },
            "synflow": {
                "score": 2.7795478858330144e+31,
                "time": 1.225590467453003
            },
            "grad_sign": {
                "score": 3.8648431301116943,
                "time": 5.023176431655884
            },
            "snip": {
                "score": 51.100990295410156,
                "time": 1.7346513271331787
            },
            "grad_norm": {
                "score": 7.545960903167725,
                "time": 1.898144006729126
            },
            "epe_nas": {
                "score": 105.71685684240819,
                "time": 1.8471412658691406
            },
            "grasp": {
                "score": -71.640869140625,
                "time": 13.103467464447021
            },
            "fisher": {
                "score": 625.07763671875,
                "time": 1.8466289043426514
            },
            "l2_norm": {
                "score": 1307.91162109375,
                "time": 0.005320310592651367
            },
            "jacov": {
                "score": -27.375302296265453,
                "time": 1.566758155822754
            },
            "zen": {
                "score": 57.158172607421875,
                "time": 1.1315572261810303
            },
            "nwot": {
                "score": 220.194363063676,
                "time": 1.065948486328125
            }
        },
        "zero_cost_scores_0": {
            "plain": {
                "score": -0.5372218489646912,
                "time": 1.5526032447814941
            },
            "params": {
                "score": 4513632,
                "time": 0.9970264434814453
            },
            "flops": {
                "score": 1015520342400,
                "time": 1.2455883026123047
            },
            "synflow": {
                "score": 2.4469389758003945e+24,
                "time": 1.3377649784088135
            },
            "grad_sign": {
                "score": 5.272008419036865,
                "time": 3.5837643146514893
            },
            "snip": {
                "score": 38.91590118408203,
                "time": 1.6406323909759521
            },
            "grad_norm": {
                "score": 6.730662822723389,
                "time": 1.6655199527740479
            },
            "epe_nas": {
                "score": 5.313064710969748,
                "time": 1.8760619163513184
            },
            "grasp": {
                "score": -4.739157199859619,
                "time": 12.644387245178223
            },
            "fisher": {
                "score": 537.7749633789062,
                "time": 1.8662519454956055
            },
            "l2_norm": {
                "score": 693.4078369140625,
                "time": 0.005530595779418945
            },
            "jacov": {
                "score": -48.101916975776575,
                "time": 1.698258399963379
            },
            "zen": {
                "score": 57.91793441772461,
                "time": 1.222602128982544
            },
            "nwot": {
                "score": 210.81073885124047,
                "time": 1.1607692241668701
            }
        },
        "zero_cost_scores_1": {
            "plain": {
                "score": 0.5475099086761475,
                "time": 1.6137044429779053
            },
            "params": {
                "score": 4513632,
                "time": 1.1085975170135498
            },
            "flops": {
                "score": 1015520342400,
                "time": 1.1323215961456299
            },
            "synflow": {
                "score": 3.8652330287115446e+24,
                "time": 1.4573240280151367
            },
            "grad_sign": {
                "score": 4.841966152191162,
                "time": 3.614994525909424
            },
            "snip": {
                "score": 37.203060150146484,
                "time": 1.5470046997070312
            },
            "grad_norm": {
                "score": 7.520164489746094,
                "time": 1.5245511531829834
            },
            "epe_nas": {
                "score": 5.794198430422826,
                "time": 1.7551143169403076
            },
            "grasp": {
                "score": -95.2656021118164,
                "time": 12.685140132904053
            },
            "fisher": {
                "score": 589.7513427734375,
                "time": 1.8715198040008545
            },
            "l2_norm": {
                "score": 578.26171875,
                "time": 0.005358695983886719
            },
            "jacov": {
                "score": -100035.26262473837,
                "time": 1.6588306427001953
            },
            "zen": {
                "score": 58.310237884521484,
                "time": 1.2868013381958008
            },
            "nwot": {
                "score": 92.00777471689373,
                "time": 1.2826566696166992
            }
        },
        "zero_cost_scores_2": {
            "plain": {
                "score": 0.03593168035149574,
                "time": 1.666898488998413
            },
            "params": {
                "score": 4513632,
                "time": 0.8887603282928467
            },
            "flops": {
                "score": 1015520342400,
                "time": 1.235015630722046
            },
            "synflow": {
                "score": 5.388835338037292e+24,
                "time": 1.2303509712219238
            },
            "grad_sign": {
                "score": 5.490976810455322,
                "time": 3.4938082695007324
            },
            "snip": {
                "score": 38.165809631347656,
                "time": 1.5867810249328613
            },
            "grad_norm": {
                "score": 4.582642078399658,
                "time": 1.5893330574035645
            },
            "epe_nas": {
                "score": 2.1466712274187616,
                "time": 1.7372565269470215
            },
            "grasp": {
                "score": -17.48451805114746,
                "time": 12.691325664520264
            },
            "fisher": {
                "score": 222.34445190429688,
                "time": 1.8414757251739502
            },
            "l2_norm": {
                "score": 517.5230712890625,
                "time": 0.00537562370300293
            },
            "jacov": {
                "score": -100037.33586424154,
                "time": 1.726189136505127
            },
            "zen": {
                "score": 58.212059020996094,
                "time": 1.318105697631836
            },
            "nwot": {
                "score": 125.93605924037774,
                "time": 1.20583176612854
            }
        },
        "zero_cost_scores_3": {
            "plain": {
                "score": -0.4002133011817932,
                "time": 1.6836585998535156
            },
            "params": {
                "score": 4513632,
                "time": 0.9363558292388916
            },
            "flops": {
                "score": 1015520342400,
                "time": 1.1408412456512451
            },
            "synflow": {
                "score": 7.199894229912494e+24,
                "time": 1.2138817310333252
            },
            "grad_sign": {
                "score": 6.593362808227539,
                "time": 3.659868001937866
            },
            "snip": {
                "score": 32.76221466064453,
                "time": 1.6511001586914062
            },
            "grad_norm": {
                "score": 4.721264839172363,
                "time": 1.5231389999389648
            },
            "epe_nas": {
                "score": 3.2414873505058304,
                "time": 2.214130163192749
            },
            "grasp": {
                "score": -28.745845794677734,
                "time": 12.646843671798706
            },
            "fisher": {
                "score": 262.3498229980469,
                "time": 1.8947575092315674
            },
            "l2_norm": {
                "score": 486.9223327636719,
                "time": 0.005224943161010742
            },
            "jacov": {
                "score": -58.257761167781084,
                "time": 1.6260676383972168
            },
            "zen": {
                "score": 58.25712585449219,
                "time": 1.2189581394195557
            },
            "nwot": {
                "score": 91.62241635261252,
                "time": 1.106412649154663
            }
        },
        "zero_cost_scores_4": {
            "plain": {
                "score": -0.020741313695907593,
                "time": 1.4740781784057617
            },
            "params": {
                "score": 4513632,
                "time": 0.8991904258728027
            },
            "flops": {
                "score": 1015520342400,
                "time": 1.0710749626159668
            },
            "synflow": {
                "score": 7.722596199035416e+24,
                "time": 1.4251394271850586
            },
            "grad_sign": {
                "score": 5.533387184143066,
                "time": 3.4838268756866455
            },
            "snip": {
                "score": 28.49451446533203,
                "time": 1.7164976596832275
            },
            "grad_norm": {
                "score": 5.853948593139648,
                "time": 1.5300047397613525
            },
            "epe_nas": {
                "score": 1.6728081169546067,
                "time": 1.6992673873901367
            },
            "grasp": {
                "score": -50.35856628417969,
                "time": 12.543886423110962
            },
            "fisher": {
                "score": 316.6092224121094,
                "time": 1.90134596824646
            },
            "l2_norm": {
                "score": 471.24139404296875,
                "time": 0.005468606948852539
            },
            "jacov": {
                "score": -79.64267988393092,
                "time": 1.6425669193267822
            },
            "zen": {
                "score": 58.40125274658203,
                "time": 1.316145658493042
            },
            "nwot": {
                "score": 175.2478323952797,
                "time": 1.254875898361206
            }
        },
        "zero_cost_scores_5": {
            "plain": {
                "score": -0.1924898624420166,
                "time": 1.7445275783538818
            },
            "params": {
                "score": 4513632,
                "time": 0.9239063262939453
            },
            "flops": {
                "score": 1015520342400,
                "time": 1.0129880905151367
            },
            "synflow": {
                "score": 1.0618534512235878e+25,
                "time": 1.2136600017547607
            },
            "grad_sign": {
                "score": 5.219671249389648,
                "time": 3.538830518722534
            },
            "snip": {
                "score": 33.65790939331055,
                "time": 1.635361671447754
            },
            "grad_norm": {
                "score": 3.865124225616455,
                "time": 1.5793774127960205
            },
            "epe_nas": {
                "score": 2.436170277262086,
                "time": 1.7437007427215576
            },
            "grasp": {
                "score": -23.63371467590332,
                "time": 12.67183780670166
            },
            "fisher": {
                "score": 365.6477966308594,
                "time": 1.752983570098877
            },
            "l2_norm": {
                "score": 464.3942565917969,
                "time": 0.0053250789642333984
            },
            "jacov": {
                "score": -82.78939099137312,
                "time": 1.5119147300720215
            },
            "zen": {
                "score": 58.69116973876953,
                "time": 1.3060622215270996
            },
            "nwot": {
                "score": 227.06672889028476,
                "time": 1.1400833129882812
            }
        },
        "zero_cost_scores_6": {
            "plain": {
                "score": 0.5479379892349243,
                "time": 1.5503575801849365
            },
            "params": {
                "score": 4513632,
                "time": 0.8757951259613037
            },
            "flops": {
                "score": 1015520342400,
                "time": 1.2553999423980713
            },
            "synflow": {
                "score": 1.2811579060235645e+25,
                "time": 1.260108232498169
            },
            "grad_sign": {
                "score": 4.662096977233887,
                "time": 3.7674150466918945
            },
            "snip": {
                "score": 37.88520812988281,
                "time": 1.5881609916687012
            },
            "grad_norm": {
                "score": 7.822328090667725,
                "time": 1.8628883361816406
            },
            "epe_nas": {
                "score": 4.700611304644113,
                "time": 1.7246618270874023
            },
            "grasp": {
                "score": -160.981201171875,
                "time": 12.963068723678589
            },
            "fisher": {
                "score": 442.55462646484375,
                "time": 1.6424291133880615
            },
            "l2_norm": {
                "score": 461.8293762207031,
                "time": 0.0056591033935546875
            },
            "jacov": {
                "score": -100.16527901833337,
                "time": 1.6605076789855957
            },
            "zen": {
                "score": 58.74690246582031,
                "time": 1.5686726570129395
            },
            "nwot": {
                "score": 166.05292155910172,
                "time": 1.1330552101135254
            }
        },
        "zero_cost_scores_7": {
            "plain": {
                "score": -0.23942537605762482,
                "time": 1.471766710281372
            },
            "params": {
                "score": 4513632,
                "time": 1.0590612888336182
            },
            "flops": {
                "score": 1015520342400,
                "time": 1.0580501556396484
            },
            "synflow": {
                "score": 1.4341776278172915e+25,
                "time": 1.3328959941864014
            },
            "grad_sign": {
                "score": 5.838879108428955,
                "time": 3.5691399574279785
            },
            "snip": {
                "score": 33.287410736083984,
                "time": 1.687903881072998
            },
            "grad_norm": {
                "score": 5.7588934898376465,
                "time": 1.563188076019287
            },
            "epe_nas": {
                "score": 8.537024256036116,
                "time": 1.8142032623291016
            },
            "grasp": {
                "score": -71.56456756591797,
                "time": 12.640461921691895
            },
            "fisher": {
                "score": 434.3724670410156,
                "time": 1.6881523132324219
            },
            "l2_norm": {
                "score": 460.4554138183594,
                "time": 0.005156040191650391
            },
            "jacov": {
                "score": -128.02534148250635,
                "time": 1.6770679950714111
            },
            "zen": {
                "score": 58.408016204833984,
                "time": 1.2842636108398438
            },
            "nwot": {
                "score": 88.88627121563783,
                "time": 1.2379944324493408
            }
        },
        "zero_cost_scores_8": {
            "plain": {
                "score": -0.11107120662927628,
                "time": 1.5623810291290283
            },
            "params": {
                "score": 4513632,
                "time": 0.9958457946777344
            },
            "flops": {
                "score": 1015520342400,
                "time": 1.1219956874847412
            },
            "synflow": {
                "score": 1.2364837866026872e+25,
                "time": 1.3424766063690186
            },
            "grad_sign": {
                "score": 6.525946140289307,
                "time": 3.4810969829559326
            },
            "snip": {
                "score": 34.838722229003906,
                "time": 1.5651636123657227
            },
            "grad_norm": {
                "score": 4.549041748046875,
                "time": 1.6008274555206299
            },
            "epe_nas": {
                "score": 5.075406524060132,
                "time": 1.7481908798217773
            },
            "grasp": {
                "score": -47.90060043334961,
                "time": 12.671157121658325
            },
            "fisher": {
                "score": 310.513916015625,
                "time": 1.774167776107788
            },
            "l2_norm": {
                "score": 458.216064453125,
                "time": 0.005279541015625
            },
            "jacov": {
                "score": -87.98811644446039,
                "time": 1.6124613285064697
            },
            "zen": {
                "score": 58.444618225097656,
                "time": 1.4244637489318848
            },
            "nwot": {
                "score": 248.9554413995319,
                "time": 1.233689308166504
            }
        },
        "zero_cost_scores_9": {
            "plain": {
                "score": -0.3214326500892639,
                "time": 1.6366641521453857
            },
            "params": {
                "score": 4513632,
                "time": 0.9107053279876709
            },
            "flops": {
                "score": 1015520342400,
                "time": 1.1147470474243164
            },
            "synflow": {
                "score": 1.4085285129100766e+25,
                "time": 1.3539423942565918
            },
            "grad_sign": {
                "score": 5.693089008331299,
                "time": 3.4483470916748047
            },
            "snip": {
                "score": 35.74263381958008,
                "time": 1.6780755519866943
            },
            "grad_norm": {
                "score": 6.712794303894043,
                "time": 1.9438788890838623
            },
            "epe_nas": {
                "score": 1.441106494759359,
                "time": 1.781447410583496
            },
            "grasp": {
                "score": -78.30061340332031,
                "time": 12.669159412384033
            },
            "fisher": {
                "score": 509.48681640625,
                "time": 1.9528887271881104
            },
            "l2_norm": {
                "score": 458.5627746582031,
                "time": 0.005157947540283203
            },
            "jacov": {
                "score": -82.994939644569,
                "time": 1.7287442684173584
            },
            "zen": {
                "score": 58.353851318359375,
                "time": 1.481215238571167
            },
            "nwot": {
                "score": 112.16791041409776,
                "time": 1.1990165710449219
            }
        },
        "zero_cost_scores_11": {
            "plain": {
                "score": -0.16802939772605896,
                "time": 1.7285077571868896
            },
            "params": {
                "score": 4513632,
                "time": 0.9910619258880615
            },
            "flops": {
                "score": 1015520342400,
                "time": 1.043656587600708
            },
            "synflow": {
                "score": 5.635348972543833e+23,
                "time": 1.2939555644989014
            },
            "grad_sign": {
                "score": 5.352598667144775,
                "time": 3.586282253265381
            },
            "snip": {
                "score": 17.107322692871094,
                "time": 1.9249026775360107
            },
            "grad_norm": {
                "score": 7.278368949890137,
                "time": 1.5157527923583984
            },
            "epe_nas": {
                "score": 1.289656985432477,
                "time": 1.7642388343811035
            },
            "grasp": {
                "score": -119.62535858154297,
                "time": 12.495437622070312
            },
            "fisher": {
                "score": 236.35897827148438,
                "time": 1.932201623916626
            },
            "l2_norm": {
                "score": 427.040771484375,
                "time": 0.005205392837524414
            },
            "jacov": {
                "score": -100127.55942131544,
                "time": 1.4502055644989014
            },
            "zen": {
                "score": 57.844993591308594,
                "time": 1.1864111423492432
            },
            "nwot": {
                "score": 115.2092794563693,
                "time": 1.2093870639801025
            }
        },
        "zero_cost_scores_13": {
            "plain": {
                "score": -0.3913794457912445,
                "time": 1.5556614398956299
            },
            "params": {
                "score": 4513632,
                "time": 0.9934287071228027
            },
            "flops": {
                "score": 1015520342400,
                "time": 1.0661616325378418
            },
            "synflow": {
                "score": 1.1037471209871727e+24,
                "time": 1.4179182052612305
            },
            "grad_sign": {
                "score": 5.095690727233887,
                "time": 3.4823482036590576
            },
            "snip": {
                "score": 28.055713653564453,
                "time": 1.568317174911499
            },
            "grad_norm": {
                "score": 4.701375484466553,
                "time": 1.577043056488037
            },
            "epe_nas": {
                "score": 8.960504661701068,
                "time": 1.8430368900299072
            },
            "grasp": {
                "score": -86.26581573486328,
                "time": 12.593437194824219
            },
            "fisher": {
                "score": 304.7124938964844,
                "time": 1.8571312427520752
            },
            "l2_norm": {
                "score": 432.09539794921875,
                "time": 0.005179166793823242
            },
            "jacov": {
                "score": -183.0729634104092,
                "time": 1.6355478763580322
            },
            "zen": {
                "score": 57.55934524536133,
                "time": 1.2617409229278564
            },
            "nwot": {
                "score": 84.48289642896488,
                "time": 1.1518597602844238
            }
        },
        "zero_cost_scores_15": {
            "plain": {
                "score": -0.12040136754512787,
                "time": 1.4416687488555908
            },
            "params": {
                "score": 4513632,
                "time": 0.9810521602630615
            },
            "flops": {
                "score": 1015520342400,
                "time": 1.0719268321990967
            },
            "synflow": {
                "score": 2.64493010585696e+24,
                "time": 1.2834973335266113
            },
            "grad_sign": {
                "score": 4.884904384613037,
                "time": 3.590958595275879
            },
            "snip": {
                "score": 23.693632125854492,
                "time": 1.544689655303955
            },
            "grad_norm": {
                "score": 5.5109429359436035,
                "time": 1.546159267425537
            },
            "epe_nas": {
                "score": 4.181673294078832,
                "time": 1.8288466930389404
            },
            "grasp": {
                "score": -76.27082061767578,
                "time": 12.73947525024414
            },
            "fisher": {
                "score": 302.0115051269531,
                "time": 1.9245495796203613
            },
            "l2_norm": {
                "score": 439.41796875,
                "time": 0.005269765853881836
            },
            "jacov": {
                "score": -86.46846822305666,
                "time": 1.5893969535827637
            },
            "zen": {
                "score": 58.00593566894531,
                "time": 1.3168926239013672
            },
            "nwot": {
                "score": 110.44058872557463,
                "time": 1.3413050174713135
            }
        },
        "zero_cost_scores_17": {
            "plain": {
                "score": 0.10100860148668289,
                "time": 1.4849977493286133
            },
            "params": {
                "score": 4513632,
                "time": 0.9470255374908447
            },
            "flops": {
                "score": 1015520342400,
                "time": 1.495110273361206
            },
            "synflow": {
                "score": 4.894343686420777e+24,
                "time": 1.344372272491455
            },
            "grad_sign": {
                "score": 5.743451118469238,
                "time": 3.4668333530426025
            },
            "snip": {
                "score": 31.907922744750977,
                "time": 1.6010453701019287
            },
            "grad_norm": {
                "score": 6.99785852432251,
                "time": 1.5942530632019043
            },
            "epe_nas": {
                "score": 2.0170863419718996,
                "time": 1.7298781871795654
            },
            "grasp": {
                "score": -164.3495330810547,
                "time": 12.803544998168945
            },
            "fisher": {
                "score": 444.95355224609375,
                "time": 1.7966091632843018
            },
            "l2_norm": {
                "score": 444.0589294433594,
                "time": 0.0052225589752197266
            },
            "jacov": {
                "score": -170.41885299030713,
                "time": 2.014730453491211
            },
            "zen": {
                "score": 57.7302131652832,
                "time": 1.3135216236114502
            },
            "nwot": {
                "score": 65.53690682609177,
                "time": 1.2203078269958496
            }
        },
        "zero_cost_scores_19": {
            "plain": {
                "score": -0.4765779674053192,
                "time": 1.5791535377502441
            },
            "params": {
                "score": 4513632,
                "time": 1.0120303630828857
            },
            "flops": {
                "score": 1015520342400,
                "time": 1.1927967071533203
            },
            "synflow": {
                "score": 7.696441248194183e+24,
                "time": 1.2527663707733154
            },
            "grad_sign": {
                "score": 5.417708873748779,
                "time": 3.51399302482605
            },
            "snip": {
                "score": 28.550321578979492,
                "time": 1.721064805984497
            },
            "grad_norm": {
                "score": 7.46538782119751,
                "time": 1.4829261302947998
            },
            "epe_nas": {
                "score": 4.078892942427648,
                "time": 1.8485455513000488
            },
            "grasp": {
                "score": -129.3560791015625,
                "time": 12.890462636947632
            },
            "fisher": {
                "score": 384.398193359375,
                "time": 1.957263708114624
            },
            "l2_norm": {
                "score": 449.24462890625,
                "time": 0.005419492721557617
            },
            "jacov": {
                "score": -100100.79286908089,
                "time": 1.528559684753418
            },
            "zen": {
                "score": 58.650997161865234,
                "time": 1.2211520671844482
            },
            "nwot": {
                "score": 107.5860085219131,
                "time": 1.131044626235962
            }
        },
        "zero_cost_scores_21": {
            "plain": {
                "score": -0.3052310645580292,
                "time": 1.6493804454803467
            },
            "params": {
                "score": 4513632,
                "time": 1.0877301692962646
            },
            "flops": {
                "score": 1015520342400,
                "time": 1.0493106842041016
            },
            "synflow": {
                "score": 1.1323442133055137e+25,
                "time": 1.2138612270355225
            },
            "grad_sign": {
                "score": 5.113739967346191,
                "time": 3.4464077949523926
            },
            "snip": {
                "score": 32.81515121459961,
                "time": 1.7095670700073242
            },
            "grad_norm": {
                "score": 3.9938251972198486,
                "time": 1.5616447925567627
            },
            "epe_nas": {
                "score": 4.8307812396769325,
                "time": 1.7009634971618652
            },
            "grasp": {
                "score": -99.15584564208984,
                "time": 12.624339818954468
            },
            "fisher": {
                "score": 283.37860107421875,
                "time": 1.7855756282806396
            },
            "l2_norm": {
                "score": 452.64593505859375,
                "time": 0.0052182674407958984
            },
            "jacov": {
                "score": -101.26674078687996,
                "time": 1.495215654373169
            },
            "zen": {
                "score": 58.184783935546875,
                "time": 1.2628974914550781
            },
            "nwot": {
                "score": 169.69762059139367,
                "time": 1.2104675769805908
            }
        },
        "zero_cost_scores_23": {
            "plain": {
                "score": -0.2666480839252472,
                "time": 1.5424838066101074
            },
            "params": {
                "score": 4513632,
                "time": 0.9371747970581055
            },
            "flops": {
                "score": 1015520342400,
                "time": 1.2097890377044678
            },
            "synflow": {
                "score": 1.5188589478734915e+25,
                "time": 1.2790753841400146
            },
            "grad_sign": {
                "score": 5.0109357833862305,
                "time": 3.651613473892212
            },
            "snip": {
                "score": 28.765789031982422,
                "time": 1.5949866771697998
            },
            "grad_norm": {
                "score": 6.460608959197998,
                "time": 1.6054222583770752
            },
            "epe_nas": {
                "score": 5.577133513036108,
                "time": 1.7578167915344238
            },
            "grasp": {
                "score": -104.13197326660156,
                "time": 12.933130979537964
            },
            "fisher": {
                "score": 486.0431213378906,
                "time": 1.8137073516845703
            },
            "l2_norm": {
                "score": 456.6392822265625,
                "time": 0.005305290222167969
            },
            "jacov": {
                "score": -200078.5995970163,
                "time": 1.693404197692871
            },
            "zen": {
                "score": 58.415184020996094,
                "time": 1.3892078399658203
            },
            "nwot": {
                "score": 82.60513160709955,
                "time": 1.1855604648590088
            }
        },
        "zero_cost_scores_25": {
            "plain": {
                "score": 1.3896896839141846,
                "time": 1.5524792671203613
            },
            "params": {
                "score": 4513632,
                "time": 0.9929049015045166
            },
            "flops": {
                "score": 1015520342400,
                "time": 1.1956939697265625
            },
            "synflow": {
                "score": 1.8034257076719811e+25,
                "time": 1.1636154651641846
            },
            "grad_sign": {
                "score": 5.864579677581787,
                "time": 3.5111289024353027
            },
            "snip": {
                "score": 35.26669692993164,
                "time": 1.5589537620544434
            },
            "grad_norm": {
                "score": 7.673964500427246,
                "time": 2.1014418601989746
            },
            "epe_nas": {
                "score": 2.866976900083764,
                "time": 1.7317569255828857
            },
            "grasp": {
                "score": -106.11114501953125,
                "time": 12.557097673416138
            },
            "fisher": {
                "score": 445.9788818359375,
                "time": 1.7689433097839355
            },
            "l2_norm": {
                "score": 458.73480224609375,
                "time": 0.005490303039550781
            },
            "jacov": {
                "score": -139.35578914365016,
                "time": 1.5818989276885986
            },
            "zen": {
                "score": 58.708229064941406,
                "time": 1.3327019214630127
            },
            "nwot": {
                "score": 165.3126801665815,
                "time": 1.1158483028411865
            }
        },
        "zero_cost_scores_27": {
            "plain": {
                "score": -0.22940205037593842,
                "time": 1.4287939071655273
            },
            "params": {
                "score": 4513632,
                "time": 1.162224531173706
            },
            "flops": {
                "score": 1015520342400,
                "time": 1.1934177875518799
            },
            "synflow": {
                "score": 2.3440889756739194e+25,
                "time": 1.3123083114624023
            },
            "grad_sign": {
                "score": 5.861114025115967,
                "time": 3.4721686840057373
            },
            "snip": {
                "score": 36.307281494140625,
                "time": 1.6190252304077148
            },
            "grad_norm": {
                "score": 8.444257736206055,
                "time": 1.5860881805419922
            },
            "epe_nas": {
                "score": 0.9733469386101941,
                "time": 1.760329008102417
            },
            "grasp": {
                "score": -154.19004821777344,
                "time": 12.57714581489563
            },
            "fisher": {
                "score": 506.06610107421875,
                "time": 1.8907158374786377
            },
            "l2_norm": {
                "score": 461.83343505859375,
                "time": 0.005529165267944336
            },
            "jacov": {
                "score": -100.78308273362826,
                "time": 1.5185611248016357
            },
            "zen": {
                "score": 58.630435943603516,
                "time": 1.561063289642334
            },
            "nwot": {
                "score": 122.03125380463833,
                "time": 1.234339952468872
            }
        },
        "zero_cost_scores_29": {
            "plain": {
                "score": 0.1904018074274063,
                "time": 1.5327301025390625
            },
            "params": {
                "score": 4513632,
                "time": 0.980522871017456
            },
            "flops": {
                "score": 1015520342400,
                "time": 1.079805612564087
            },
            "synflow": {
                "score": 2.6678629470009106e+25,
                "time": 1.463740587234497
            },
            "grad_sign": {
                "score": 5.0332865715026855,
                "time": 3.802741765975952
            },
            "snip": {
                "score": 30.140363693237305,
                "time": 1.6351110935211182
            },
            "grad_norm": {
                "score": 6.123645305633545,
                "time": 1.7263007164001465
            },
            "epe_nas": {
                "score": 3.0341259425079823,
                "time": 1.733785629272461
            },
            "grasp": {
                "score": -110.61730194091797,
                "time": 12.642321109771729
            },
            "fisher": {
                "score": 335.8013916015625,
                "time": 1.7227344512939453
            },
            "l2_norm": {
                "score": 463.48712158203125,
                "time": 0.005457401275634766
            },
            "jacov": {
                "score": -100120.37078888828,
                "time": 1.5987765789031982
            },
            "zen": {
                "score": 58.491573333740234,
                "time": 1.3526489734649658
            },
            "nwot": {
                "score": 246.90103610734738,
                "time": 1.2057907581329346
            }
        },
        "zero_cost_scores_31": {
            "plain": {
                "score": -0.22296404838562012,
                "time": 1.6013965606689453
            },
            "params": {
                "score": 4513632,
                "time": 0.9056997299194336
            },
            "flops": {
                "score": 1015520342400,
                "time": 1.106492519378662
            },
            "synflow": {
                "score": 4.308118219807724e+24,
                "time": 1.306729793548584
            },
            "grad_sign": {
                "score": 5.642107009887695,
                "time": 3.524646282196045
            },
            "snip": {
                "score": 32.27165603637695,
                "time": 1.4351541996002197
            },
            "grad_norm": {
                "score": 7.65070104598999,
                "time": 1.5453426837921143
            },
            "epe_nas": {
                "score": 0.2958915375001091,
                "time": 1.766730785369873
            },
            "grasp": {
                "score": -92.26078033447266,
                "time": 12.579323291778564
            },
            "fisher": {
                "score": 420.7965393066406,
                "time": 2.1125576496124268
            },
            "l2_norm": {
                "score": 444.1808776855469,
                "time": 0.005431175231933594
            },
            "jacov": {
                "score": -229.06540864912256,
                "time": 1.8134806156158447
            },
            "zen": {
                "score": 57.77983093261719,
                "time": 1.277761697769165
            },
            "nwot": {
                "score": 110.26358701366493,
                "time": 1.2485482692718506
            }
        },
        "zero_cost_scores_33": {
            "plain": {
                "score": -0.1172778308391571,
                "time": 1.8184385299682617
            },
            "params": {
                "score": 4513632,
                "time": 0.9732372760772705
            },
            "flops": {
                "score": 1015520342400,
                "time": 1.097886085510254
            },
            "synflow": {
                "score": 8.282304775215098e+23,
                "time": 1.4708597660064697
            },
            "grad_sign": {
                "score": 4.258950710296631,
                "time": 3.472485303878784
            },
            "snip": {
                "score": 28.080650329589844,
                "time": 1.586604356765747
            },
            "grad_norm": {
                "score": 5.853212833404541,
                "time": 1.663733959197998
            },
            "epe_nas": {
                "score": 3.9173404164093832,
                "time": 1.8074123859405518
            },
            "grasp": {
                "score": -98.45207214355469,
                "time": 12.621445894241333
            },
            "fisher": {
                "score": 374.5051574707031,
                "time": 1.8138465881347656
            },
            "l2_norm": {
                "score": 428.308349609375,
                "time": 0.0054247379302978516
            },
            "jacov": {
                "score": -137.0636765648327,
                "time": 1.683048963546753
            },
            "zen": {
                "score": 57.797157287597656,
                "time": 1.3668749332427979
            },
            "nwot": {
                "score": 235.26723942020422,
                "time": 1.2006731033325195
            }
        },
        "zero_cost_scores_35": {
            "plain": {
                "score": 0.17011967301368713,
                "time": 1.507620096206665
            },
            "params": {
                "score": 4513632,
                "time": 1.077312707901001
            },
            "flops": {
                "score": 1015520342400,
                "time": 1.0525953769683838
            },
            "synflow": {
                "score": 2.0575033813832752e+23,
                "time": 1.1239287853240967
            },
            "grad_sign": {
                "score": 6.052489280700684,
                "time": 3.5447864532470703
            },
            "snip": {
                "score": 30.89967155456543,
                "time": 1.6676833629608154
            },
            "grad_norm": {
                "score": 6.000967025756836,
                "time": 1.6953792572021484
            },
            "epe_nas": {
                "score": 1.4071875072326674,
                "time": 1.8619532585144043
            },
            "grasp": {
                "score": -94.16670227050781,
                "time": 12.577964782714844
            },
            "fisher": {
                "score": 235.45790100097656,
                "time": 1.6895551681518555
            },
            "l2_norm": {
                "score": 415.7535400390625,
                "time": 0.005484819412231445
            },
            "jacov": {
                "score": -179.81071794032135,
                "time": 1.6635212898254395
            },
            "zen": {
                "score": 57.54292297363281,
                "time": 1.477217197418213
            },
            "nwot": {
                "score": 88.15051384530453,
                "time": 1.1753737926483154
            }
        },
        "zero_cost_scores_37": {
            "plain": {
                "score": -0.18337193131446838,
                "time": 1.57724928855896
            },
            "params": {
                "score": 4513632,
                "time": 1.0188343524932861
            },
            "flops": {
                "score": 1015520342400,
                "time": 1.108959436416626
            },
            "synflow": {
                "score": 6.813392324526549e+22,
                "time": 1.2559068202972412
            },
            "grad_sign": {
                "score": 4.896899700164795,
                "time": 3.4728758335113525
            },
            "snip": {
                "score": 26.431438446044922,
                "time": 1.5439422130584717
            },
            "grad_norm": {
                "score": 5.556131362915039,
                "time": 1.6617887020111084
            },
            "epe_nas": {
                "score": 7.203379803700019,
                "time": 1.7067956924438477
            },
            "grasp": {
                "score": -95.91574096679688,
                "time": 12.705257415771484
            },
            "fisher": {
                "score": 264.6946105957031,
                "time": 1.8624987602233887
            },
            "l2_norm": {
                "score": 406.41583251953125,
                "time": 0.005373716354370117
            },
            "jacov": {
                "score": -100140.80530699166,
                "time": 1.6304163932800293
            },
            "zen": {
                "score": 57.19829559326172,
                "time": 1.272118330001831
            },
            "nwot": {
                "score": 104.70219799041848,
                "time": 1.3323519229888916
            }
        },
        "zero_cost_scores_39": {
            "plain": {
                "score": -0.23426516354084015,
                "time": 1.6489169597625732
            },
            "params": {
                "score": 4513632,
                "time": 0.9071924686431885
            },
            "flops": {
                "score": 1015520342400,
                "time": 1.1800248622894287
            },
            "synflow": {
                "score": 3.110319692750981e+22,
                "time": 1.236175775527954
            },
            "grad_sign": {
                "score": 4.777874946594238,
                "time": 3.49468731880188
            },
            "snip": {
                "score": 27.15924644470215,
                "time": 1.678011178970337
            },
            "grad_norm": {
                "score": 5.554135322570801,
                "time": 1.5600557327270508
            },
            "epe_nas": {
                "score": 6.0689687298288,
                "time": 1.8585901260375977
            },
            "grasp": {
                "score": -79.86766815185547,
                "time": 12.717781782150269
            },
            "fisher": {
                "score": 232.0934600830078,
                "time": 1.9691882133483887
            },
            "l2_norm": {
                "score": 400.12408447265625,
                "time": 0.005313873291015625
            },
            "jacov": {
                "score": -193.79137236566908,
                "time": 1.4817888736724854
            },
            "zen": {
                "score": 57.26866149902344,
                "time": 1.3341317176818848
            },
            "nwot": {
                "score": 106.52618319126383,
                "time": 1.2643487453460693
            }
        },
        "zero_cost_scores_41": {
            "plain": {
                "score": -0.13234026730060577,
                "time": 1.4826934337615967
            },
            "params": {
                "score": 4513632,
                "time": 1.0535430908203125
            },
            "flops": {
                "score": 1015520342400,
                "time": 1.196589708328247
            },
            "synflow": {
                "score": 1.7835646869149923e+22,
                "time": 1.5130994319915771
            },
            "grad_sign": {
                "score": 4.834871292114258,
                "time": 3.455204486846924
            },
            "snip": {
                "score": 25.747638702392578,
                "time": 1.6104226112365723
            },
            "grad_norm": {
                "score": 5.193157196044922,
                "time": 1.594538927078247
            },
            "epe_nas": {
                "score": 4.025385869117845,
                "time": 1.6654183864593506
            },
            "grasp": {
                "score": -79.8029556274414,
                "time": 12.53681230545044
            },
            "fisher": {
                "score": 223.68699645996094,
                "time": 1.8273663520812988
            },
            "l2_norm": {
                "score": 395.95367431640625,
                "time": 0.005359649658203125
            },
            "jacov": {
                "score": -185.99401830781426,
                "time": 1.5628881454467773
            },
            "zen": {
                "score": 56.674530029296875,
                "time": 1.1946074962615967
            },
            "nwot": {
                "score": 129.86775795249028,
                "time": 1.263578176498413
            }
        },
        "zero_cost_scores_43": {
            "plain": {
                "score": -0.3875621557235718,
                "time": 1.4983201026916504
            },
            "params": {
                "score": 4513632,
                "time": 0.9087281227111816
            },
            "flops": {
                "score": 1015520342400,
                "time": 1.0151495933532715
            },
            "synflow": {
                "score": 1.3469167317185196e+22,
                "time": 1.2211251258850098
            },
            "grad_sign": {
                "score": 4.236576080322266,
                "time": 3.5016391277313232
            },
            "snip": {
                "score": 25.941617965698242,
                "time": 1.7290029525756836
            },
            "grad_norm": {
                "score": 5.919726371765137,
                "time": 1.6170876026153564
            },
            "epe_nas": {
                "score": 13.55782761615919,
                "time": 1.792475938796997
            },
            "grasp": {
                "score": -81.94024658203125,
                "time": 12.625115156173706
            },
            "fisher": {
                "score": 207.563232421875,
                "time": 1.8197860717773438
            },
            "l2_norm": {
                "score": 393.6716613769531,
                "time": 0.005167245864868164
            },
            "jacov": {
                "score": -83.2232496710344,
                "time": 1.7367722988128662
            },
            "zen": {
                "score": 57.209686279296875,
                "time": 1.481790542602539
            },
            "nwot": {
                "score": 107.47207264252103,
                "time": 1.1415746212005615
            }
        },
        "zero_cost_scores_45": {
            "plain": {
                "score": -0.13030163943767548,
                "time": 1.6098904609680176
            },
            "params": {
                "score": 4513632,
                "time": 1.0394244194030762
            },
            "flops": {
                "score": 1015520342400,
                "time": 1.182748794555664
            },
            "synflow": {
                "score": 1.1184269169282725e+22,
                "time": 1.4657599925994873
            },
            "grad_sign": {
                "score": 3.761653423309326,
                "time": 3.6296098232269287
            },
            "snip": {
                "score": 26.877756118774414,
                "time": 1.5231750011444092
            },
            "grad_norm": {
                "score": 5.194910049438477,
                "time": 1.5310795307159424
            },
            "epe_nas": {
                "score": 4.52534060904594,
                "time": 2.023606300354004
            },
            "grasp": {
                "score": -59.777156829833984,
                "time": 12.614628076553345
            },
            "fisher": {
                "score": 289.05670166015625,
                "time": 1.873769760131836
            },
            "l2_norm": {
                "score": 392.2404479980469,
                "time": 0.005519866943359375
            },
            "jacov": {
                "score": -189.64781102431394,
                "time": 1.4281730651855469
            },
            "zen": {
                "score": 56.877906799316406,
                "time": 1.2845447063446045
            },
            "nwot": {
                "score": 189.4185364355581,
                "time": 1.1354191303253174
            }
        }
    }
}