{
    "f4b8cce95a660d9b080ab9d4edfc76ae7cfd93d2a3d763e4034eab0c36ff2644": {
        "weights": [
            [
                0.06362257000350341,
                0.12206294036826268,
                0.0911535393365387,
                0.07733458350118304,
                0.10727513001300035,
                0.14268081968476856,
                0.1361577386007925,
                0.14823881158299268
            ],
            [
                0.13314915060160365,
                0.13485444730783114,
                0.10325068233301077,
                0.08183767166331737,
                0.11695406660349737,
                0.12492154467826315,
                0.1454541369826707,
                0.06136072732753185
            ],
            [
                0.1260769630710124,
                0.10821770839234633,
                0.08217846416241577,
                0.09044217601126017,
                0.1148700172679062,
                0.10711812214765404,
                0.1446523602650119,
                0.11063811161227466
            ],
            [
                0.11761462913085786,
                0.050780853303108046,
                0.10310168071243866,
                0.06942779846124995,
                0.11657864012186522,
                0.14256629825155642,
                0.05128406383041728,
                0.0806902613423865
            ]
        ],
        "val_acc": 0.9344409282700422,
        "time": 25354.140461206436,
        "zero_cost_scores": {
            "plain": {
                "score": 3.4504802227020264,
                "time": 4.223896026611328
            },
            "params": {
                "score": 3010164,
                "time": 1.6447315216064453
            },
            "flops": {
                "score": 1269182020800,
                "time": 2.0805823802948
            },
            "synflow": {
                "score": 289228546453776.2,
                "time": 1.9805283546447754
            },
            "grad_sign": {
                "score": 3.0977699756622314,
                "time": 3.769815444946289
            },
            "snip": {
                "score": 49.77074432373047,
                "time": 1.9443910121917725
            },
            "grad_norm": {
                "score": 6.788125038146973,
                "time": 1.902219533920288
            },
            "epe_nas": {
                "score": 5.160635142979958,
                "time": 1.422067403793335
            },
            "grasp": {
                "score": -20.009746551513672,
                "time": 3.7878715991973877
            },
            "fisher": {
                "score": 848.3983154296875,
                "time": 2.3774585723876953
            },
            "l2_norm": {
                "score": 877.5829467773438,
                "time": 0.0033190250396728516
            },
            "jacov": {
                "score": -101.5483140819875,
                "time": 1.9962208271026611
            },
            "zen": {
                "score": 34.473060607910156,
                "time": 2.104830741882324
            },
            "nwot": {
                "score": 200.50486894414877,
                "time": 1.7061386108398438
            }
        },
        "zero_cost_scores_0": {
            "plain": {
                "score": 0.29913854598999023,
                "time": 1.9919841289520264
            },
            "params": {
                "score": 3010164,
                "time": 1.4396686553955078
            },
            "flops": {
                "score": 1269182020800,
                "time": 1.4591641426086426
            },
            "synflow": {
                "score": 690600965186604.8,
                "time": 1.772707223892212
            },
            "grad_sign": {
                "score": 4.991556167602539,
                "time": 2.4141626358032227
            },
            "snip": {
                "score": 39.688507080078125,
                "time": 2.0307209491729736
            },
            "grad_norm": {
                "score": 7.352477073669434,
                "time": 2.181776285171509
            },
            "epe_nas": {
                "score": 2.7889256472943598,
                "time": 1.3961570262908936
            },
            "grasp": {
                "score": -19.886852264404297,
                "time": 3.6288633346557617
            },
            "fisher": {
                "score": 222.7662353515625,
                "time": 1.9070806503295898
            },
            "l2_norm": {
                "score": 592.676513671875,
                "time": 0.0033464431762695312
            },
            "jacov": {
                "score": -173.6821789484298,
                "time": 2.107863426208496
            },
            "zen": {
                "score": 33.80628204345703,
                "time": 1.5892751216888428
            },
            "nwot": {
                "score": 202.48622082101457,
                "time": 1.8939752578735352
            }
        },
        "zero_cost_scores_1": {
            "plain": {
                "score": 0.11518672108650208,
                "time": 1.668386459350586
            },
            "params": {
                "score": 3010164,
                "time": 1.5179173946380615
            },
            "flops": {
                "score": 1269182020800,
                "time": 1.7392375469207764
            },
            "synflow": {
                "score": 2501965035750377.5,
                "time": 1.6029198169708252
            },
            "grad_sign": {
                "score": 4.589200496673584,
                "time": 2.4576592445373535
            },
            "snip": {
                "score": 46.473976135253906,
                "time": 1.9341211318969727
            },
            "grad_norm": {
                "score": 7.085482597351074,
                "time": 1.9808084964752197
            },
            "epe_nas": {
                "score": 0.3838419460612482,
                "time": 1.3945529460906982
            },
            "grasp": {
                "score": -22.96541404724121,
                "time": 3.059782028198242
            },
            "fisher": {
                "score": 158.7518310546875,
                "time": 2.3036246299743652
            },
            "l2_norm": {
                "score": 441.61199951171875,
                "time": 0.0033555030822753906
            },
            "jacov": {
                "score": -100414.32808340491,
                "time": 2.020087718963623
            },
            "zen": {
                "score": 33.92683410644531,
                "time": 1.5553407669067383
            },
            "nwot": {
                "score": 329.34743244351444,
                "time": 1.706775188446045
            }
        },
        "zero_cost_scores_2": {
            "plain": {
                "score": -0.1905396431684494,
                "time": 1.599769115447998
            },
            "params": {
                "score": 3010164,
                "time": 1.2838752269744873
            },
            "flops": {
                "score": 1269182020800,
                "time": 1.5466432571411133
            },
            "synflow": {
                "score": 6787092904551566.0,
                "time": 1.4996278285980225
            },
            "grad_sign": {
                "score": 3.8362810611724854,
                "time": 2.6636900901794434
            },
            "snip": {
                "score": 35.23983383178711,
                "time": 1.6825942993164062
            },
            "grad_norm": {
                "score": 3.739145517349243,
                "time": 1.8868067264556885
            },
            "epe_nas": {
                "score": 0.4409233701802024,
                "time": 1.4414660930633545
            },
            "grasp": {
                "score": -6.46577787399292,
                "time": 3.04603910446167
            },
            "fisher": {
                "score": 88.92302703857422,
                "time": 2.156186580657959
            },
            "l2_norm": {
                "score": 364.0950927734375,
                "time": 0.003438234329223633
            },
            "jacov": {
                "score": -700.2599441462523,
                "time": 1.5974724292755127
            },
            "zen": {
                "score": 33.86166763305664,
                "time": 1.4798576831817627
            },
            "nwot": {
                "score": 252.00251839796306,
                "time": 2.8378872871398926
            }
        },
        "zero_cost_scores_3": {
            "plain": {
                "score": -0.27394047379493713,
                "time": 3.0981550216674805
            },
            "params": {
                "score": 3010164,
                "time": 3.082956552505493
            },
            "flops": {
                "score": 1269182020800,
                "time": 3.026954174041748
            },
            "synflow": {
                "score": 1.1253934813304016e+16,
                "time": 3.1572325229644775
            },
            "grad_sign": {
                "score": 4.081357002258301,
                "time": 2.4509687423706055
            },
            "snip": {
                "score": 38.53316879272461,
                "time": 4.23344087600708
            },
            "grad_norm": {
                "score": 4.288226127624512,
                "time": 3.265119791030884
            },
            "epe_nas": {
                "score": 1.2120925395777613,
                "time": 1.4995269775390625
            },
            "grasp": {
                "score": -4.106128215789795,
                "time": 3.8613836765289307
            },
            "fisher": {
                "score": 75.68781280517578,
                "time": 3.122492790222168
            },
            "l2_norm": {
                "score": 320.87322998046875,
                "time": 0.003358602523803711
            },
            "jacov": {
                "score": -603.1569545500988,
                "time": 2.7722203731536865
            },
            "zen": {
                "score": 34.27935028076172,
                "time": 2.4176831245422363
            },
            "nwot": {
                "score": 150.37451284076388,
                "time": 2.410417318344116
            }
        },
        "zero_cost_scores_4": {
            "plain": {
                "score": -0.25573092699050903,
                "time": 2.862421751022339
            },
            "params": {
                "score": 3010164,
                "time": 2.8757948875427246
            },
            "flops": {
                "score": 1269182020800,
                "time": 3.6555943489074707
            },
            "synflow": {
                "score": 1.5571966080855454e+16,
                "time": 2.2453789710998535
            },
            "grad_sign": {
                "score": 4.708284854888916,
                "time": 2.4352009296417236
            },
            "snip": {
                "score": 34.628173828125,
                "time": 2.3878440856933594
            },
            "grad_norm": {
                "score": 4.344836711883545,
                "time": 2.6562678813934326
            },
            "epe_nas": {
                "score": 6.070274964066099,
                "time": 1.37245512008667
            },
            "grasp": {
                "score": -4.431516647338867,
                "time": 3.6544852256774902
            },
            "fisher": {
                "score": 77.66615295410156,
                "time": 2.681993007659912
            },
            "l2_norm": {
                "score": 298.54205322265625,
                "time": 0.00347900390625
            },
            "jacov": {
                "score": -324.99355409296317,
                "time": 2.682008743286133
            },
            "zen": {
                "score": 33.980186462402344,
                "time": 2.8847947120666504
            },
            "nwot": {
                "score": 38.90080694647659,
                "time": 2.2371366024017334
            }
        },
        "zero_cost_scores_5": {
            "plain": {
                "score": -0.06968367099761963,
                "time": 3.1162779331207275
            },
            "params": {
                "score": 3010164,
                "time": 2.027801752090454
            },
            "flops": {
                "score": 1269182020800,
                "time": 2.258554220199585
            },
            "synflow": {
                "score": 1.929715552060068e+16,
                "time": 2.0936245918273926
            },
            "grad_sign": {
                "score": 5.742005825042725,
                "time": 2.342301845550537
            },
            "snip": {
                "score": 37.06846237182617,
                "time": 1.9792861938476562
            },
            "grad_norm": {
                "score": 4.2774481773376465,
                "time": 2.2588064670562744
            },
            "epe_nas": {
                "score": 2.023421420713384,
                "time": 1.382871150970459
            },
            "grasp": {
                "score": -6.0254316329956055,
                "time": 3.638896942138672
            },
            "fisher": {
                "score": 89.82252502441406,
                "time": 2.709120512008667
            },
            "l2_norm": {
                "score": 285.2747802734375,
                "time": 0.003325939178466797
            },
            "jacov": {
                "score": -100364.47070766494,
                "time": 2.1603901386260986
            },
            "zen": {
                "score": 34.0242805480957,
                "time": 2.0892457962036133
            },
            "nwot": {
                "score": 194.95063714461355,
                "time": 2.17071270942688
            }
        },
        "zero_cost_scores_6": {
            "plain": {
                "score": -0.27942758798599243,
                "time": 2.1868536472320557
            },
            "params": {
                "score": 3010164,
                "time": 1.9639253616333008
            },
            "flops": {
                "score": 1269182020800,
                "time": 1.7015693187713623
            },
            "synflow": {
                "score": 2.3521736314155164e+16,
                "time": 2.1162099838256836
            },
            "grad_sign": {
                "score": 4.908014297485352,
                "time": 2.3550331592559814
            },
            "snip": {
                "score": 29.30803108215332,
                "time": 1.8157641887664795
            },
            "grad_norm": {
                "score": 3.890899419784546,
                "time": 2.2006940841674805
            },
            "epe_nas": {
                "score": 0.0001999990000079768,
                "time": 1.4050424098968506
            },
            "grasp": {
                "score": -4.731971740722656,
                "time": 3.3379087448120117
            },
            "fisher": {
                "score": 79.44174194335938,
                "time": 2.412743330001831
            },
            "l2_norm": {
                "score": 279.38983154296875,
                "time": 0.0032987594604492188
            },
            "jacov": {
                "score": -200304.63546341736,
                "time": 2.6227192878723145
            },
            "zen": {
                "score": 34.305965423583984,
                "time": 2.2406961917877197
            },
            "nwot": {
                "score": 170.3972291979802,
                "time": 1.6980855464935303
            }
        },
        "zero_cost_scores_7": {
            "plain": {
                "score": -0.3818642497062683,
                "time": 1.9978632926940918
            },
            "params": {
                "score": 3010164,
                "time": 1.5556533336639404
            },
            "flops": {
                "score": 1269182020800,
                "time": 1.6205532550811768
            },
            "synflow": {
                "score": 2.542169800031246e+16,
                "time": 1.7974061965942383
            },
            "grad_sign": {
                "score": 4.674931049346924,
                "time": 2.387587785720825
            },
            "snip": {
                "score": 28.171125411987305,
                "time": 1.9318416118621826
            },
            "grad_norm": {
                "score": 5.248847961425781,
                "time": 2.1275463104248047
            },
            "epe_nas": {
                "score": 4.144827398924381,
                "time": 1.4902832508087158
            },
            "grasp": {
                "score": -12.672826766967773,
                "time": 3.102536201477051
            },
            "fisher": {
                "score": 134.5689239501953,
                "time": 2.4317710399627686
            },
            "l2_norm": {
                "score": 275.28375244140625,
                "time": 0.0033349990844726562
            },
            "jacov": {
                "score": -317.945663891924,
                "time": 2.032419204711914
            },
            "zen": {
                "score": 34.132205963134766,
                "time": 1.9829583168029785
            },
            "nwot": {
                "score": 224.81016869187735,
                "time": 1.8626031875610352
            }
        },
        "zero_cost_scores_8": {
            "plain": {
                "score": -0.16290639340877533,
                "time": 1.8106422424316406
            },
            "params": {
                "score": 3010164,
                "time": 1.3435583114624023
            },
            "flops": {
                "score": 1269182020800,
                "time": 1.548210859298706
            },
            "synflow": {
                "score": 2.666860566979548e+16,
                "time": 1.5240485668182373
            },
            "grad_sign": {
                "score": 5.363829135894775,
                "time": 2.423210859298706
            },
            "snip": {
                "score": 36.2050895690918,
                "time": 1.7961714267730713
            },
            "grad_norm": {
                "score": 4.50766134262085,
                "time": 1.862194538116455
            },
            "epe_nas": {
                "score": 2.3020500445370473,
                "time": 1.4602560997009277
            },
            "grasp": {
                "score": -7.592754364013672,
                "time": 3.311583995819092
            },
            "fisher": {
                "score": 212.45628356933594,
                "time": 2.2145748138427734
            },
            "l2_norm": {
                "score": 272.719482421875,
                "time": 0.003320455551147461
            },
            "jacov": {
                "score": -607.1975593391858,
                "time": 1.9114136695861816
            },
            "zen": {
                "score": 34.12468719482422,
                "time": 1.6659643650054932
            },
            "nwot": {
                "score": 227.1263729116303,
                "time": 1.4247689247131348
            }
        },
        "zero_cost_scores_9": {
            "plain": {
                "score": -0.031182244420051575,
                "time": 1.7450518608093262
            },
            "params": {
                "score": 3010164,
                "time": 2.025327444076538
            },
            "flops": {
                "score": 1269182020800,
                "time": 1.7281122207641602
            },
            "synflow": {
                "score": 3.028576357080957e+16,
                "time": 1.361426830291748
            },
            "grad_sign": {
                "score": 4.869378566741943,
                "time": 2.4632527828216553
            },
            "snip": {
                "score": 26.88843536376953,
                "time": 1.8271665573120117
            },
            "grad_norm": {
                "score": 4.986308574676514,
                "time": 1.8288562297821045
            },
            "epe_nas": {
                "score": 1.2779301813485873,
                "time": 1.4386539459228516
            },
            "grasp": {
                "score": -18.583271026611328,
                "time": 3.156451463699341
            },
            "fisher": {
                "score": 114.57356262207031,
                "time": 1.73417067527771
            },
            "l2_norm": {
                "score": 272.0481262207031,
                "time": 0.003401041030883789
            },
            "jacov": {
                "score": -426.6736313756153,
                "time": 1.7092037200927734
            },
            "zen": {
                "score": 34.199546813964844,
                "time": 1.5691978931427002
            },
            "nwot": {
                "score": 305.77771605837887,
                "time": 1.5034093856811523
            }
        },
        "zero_cost_scores_11": {
            "grad_sign": {
                "score": 4.819249153137207,
                "time": 2.3645875453948975
            },
            "epe_nas": {
                "score": 13.944468409485555,
                "time": 1.444784164428711
            }
        },
        "zero_cost_scores_13": {
            "grad_sign": {
                "score": 5.186162948608398,
                "time": 2.4157238006591797
            },
            "epe_nas": {
                "score": 3.808041915046632,
                "time": 1.378208875656128
            }
        },
        "zero_cost_scores_15": {
            "grad_sign": {
                "score": 5.457761287689209,
                "time": 2.364672899246216
            },
            "epe_nas": {
                "score": 13.058997927094783,
                "time": 1.518693208694458
            }
        },
        "zero_cost_scores_17": {
            "grad_sign": {
                "score": 5.405116081237793,
                "time": 2.2286229133605957
            },
            "epe_nas": {
                "score": 16.130272276714585,
                "time": 1.4478700160980225
            }
        },
        "zero_cost_scores_19": {
            "grad_sign": {
                "score": 4.279712677001953,
                "time": 2.5852339267730713
            },
            "epe_nas": {
                "score": 1.798408299886797,
                "time": 1.4883952140808105
            }
        },
        "zero_cost_scores_21": {
            "grad_sign": {
                "score": 4.812682628631592,
                "time": 2.3523495197296143
            },
            "epe_nas": {
                "score": 1.6449618362333205,
                "time": 1.4570107460021973
            }
        },
        "zero_cost_scores_23": {
            "grad_sign": {
                "score": 5.254080772399902,
                "time": 2.361753463745117
            },
            "epe_nas": {
                "score": 0.46217299540591805,
                "time": 1.3538010120391846
            }
        },
        "zero_cost_scores_25": {
            "grad_sign": {
                "score": 4.185018062591553,
                "time": 2.481107473373413
            },
            "epe_nas": {
                "score": 1.2832080651847477,
                "time": 1.5664784908294678
            }
        },
        "zero_cost_scores_27": {
            "grad_sign": {
                "score": 4.509109020233154,
                "time": 2.3860464096069336
            },
            "epe_nas": {
                "score": 1.6601365075014187,
                "time": 1.6446764469146729
            }
        },
        "zero_cost_scores_29": {
            "grad_sign": {
                "score": 4.705759048461914,
                "time": 2.463113784790039
            },
            "epe_nas": {
                "score": 1.029126574844789,
                "time": 1.50331449508667
            }
        },
        "zero_cost_scores_31": {
            "grad_sign": {
                "score": 5.6774139404296875,
                "time": 2.3623502254486084
            },
            "epe_nas": {
                "score": 3.1357794955091007,
                "time": 1.386315107345581
            }
        },
        "zero_cost_scores_33": {
            "grad_sign": {
                "score": 5.541374206542969,
                "time": 2.408463954925537
            },
            "epe_nas": {
                "score": 1.4974436636024269,
                "time": 1.4990298748016357
            }
        },
        "zero_cost_scores_35": {
            "grad_sign": {
                "score": 4.794881820678711,
                "time": 2.34182071685791
            },
            "epe_nas": {
                "score": 11.524956438218071,
                "time": 1.42268705368042
            }
        },
        "zero_cost_scores_37": {
            "grad_sign": {
                "score": 5.23914909362793,
                "time": 2.377019166946411
            },
            "epe_nas": {
                "score": 8.99515383173578,
                "time": 1.487901210784912
            }
        },
        "zero_cost_scores_39": {
            "grad_sign": {
                "score": 3.7541608810424805,
                "time": 2.3525829315185547
            },
            "epe_nas": {
                "score": 3.795307399337815,
                "time": 1.6544480323791504
            }
        },
        "zero_cost_scores_41": {
            "grad_sign": {
                "score": 3.6697518825531006,
                "time": 2.4577016830444336
            },
            "epe_nas": {
                "score": 0.9062283211829214,
                "time": 1.424060583114624
            }
        },
        "zero_cost_scores_43": {
            "grad_sign": {
                "score": 3.924866199493408,
                "time": 2.399616003036499
            },
            "epe_nas": {
                "score": 1.552891768975054,
                "time": 1.3557703495025635
            }
        },
        "zero_cost_scores_45": {
            "grad_sign": {
                "score": 3.0127625465393066,
                "time": 2.4194834232330322
            },
            "epe_nas": {
                "score": 8.510235084686151,
                "time": 1.4589323997497559
            }
        }
    }
}